jsformat/__init__.py
jsformat/dumper.py
jsformat/html.py
jsformat/json.py
jsformat/plist.py
jsformat/tree.py
jsformat/xml.py
jsformat-0.5.0.dist-info/METADATA
jsformat-0.5.0.dist-info/RECORD
jsformat-0.5.0.dist-info/WHEEL
jsformat-0.5.0.dist-info/top_level.txt
